pandabet/__init__.py
pybet/__init__.py
stakepd/__init__.py
tests/__init__.py
tests/test_pandabet.py
stakepd-0.1.3.dist-info/METADATA
stakepd-0.1.3.dist-info/WHEEL
stakepd-0.1.3.dist-info/top_level.txt
stakepd-0.1.3.dist-info/RECORD
