Metadata-Version: 2.4
Name: stakepd
Version: 0.1.3
Requires-Dist: pandas>=1.0.0
Dynamic: description
Dynamic: description-content-type
Dynamic: requires-dist
